Metadata-Version: 1.0
Name: ptspeaker
Version: 1.1.0.post1
Summary: Initialize the pi-topSPEAKER addon board
Home-page: https://pi-top.com
Author: Pi-Top
Author-email: deb-maintainer@pi-top.com
License: Apache 2.0
Platform: UNKNOWN
